sql_test_kit/__init__.py
sql_test_kit/bigquery.py
sql_test_kit/column.py
sql_test_kit/data_literals.py
sql_test_kit/interpolation_data.py
sql_test_kit/query_interpolation.py
sql_test_kit/table.py
sql_test_kit-0.4.0.dist-info/LICENSE
sql_test_kit-0.4.0.dist-info/WHEEL
sql_test_kit-0.4.0.dist-info/METADATA
sql_test_kit-0.4.0.dist-info/RECORD
