Metadata-Version: 2.1
Name: sql-test-kit
Version: 0.4.0
Summary: Framework for testing SQL queries
Author: victorlandeau
Author-email: vlandeau@gmail.com
Requires-Python: >=3.8,<3.12
Classifier: Programming Language :: Python :: 3
Classifier: Programming Language :: Python :: 3.8
Classifier: Programming Language :: Python :: 3.9
Classifier: Programming Language :: Python :: 3.10
Classifier: Programming Language :: Python :: 3.11
Provides-Extra: bigquery
Requires-Dist: db-dtypes[bigquery] (>=1.0.0)
Requires-Dist: google-cloud-bigquery[bigquery] (>=3.0.0)
Requires-Dist: pandas (>=1.0.0)
